LICENSE
MANIFEST.in
README.md
requirements.txt
setup.cfg
setup.py
GrDino/__init__.py
GrDino/version.py
GrDino.egg-info/PKG-INFO
GrDino.egg-info/SOURCES.txt
GrDino.egg-info/dependency_links.txt
GrDino.egg-info/requires.txt
GrDino.egg-info/top_level.txt
GrDino/datasets/__init__.py
GrDino/datasets/transforms.py
GrDino/models/__init__.py
GrDino/models/registry.py
GrDino/models/GroundingDINO/__init__.py
GrDino/models/GroundingDINO/bertwarper.py
GrDino/models/GroundingDINO/fuse_modules.py
GrDino/models/GroundingDINO/groundingdino.py
GrDino/models/GroundingDINO/ms_deform_attn.py
GrDino/models/GroundingDINO/transformer.py
GrDino/models/GroundingDINO/transformer_vanilla.py
GrDino/models/GroundingDINO/utils.py
GrDino/models/GroundingDINO/backbone/__init__.py
GrDino/models/GroundingDINO/backbone/backbone.py
GrDino/models/GroundingDINO/backbone/position_encoding.py
GrDino/models/GroundingDINO/backbone/swin_transformer.py
GrDino/util/__init__.py
GrDino/util/box_ops.py
GrDino/util/get_tokenlizer.py
GrDino/util/inference.py
GrDino/util/logger.py
GrDino/util/misc.py
GrDino/util/slconfig.py
GrDino/util/slio.py
GrDino/util/time_counter.py
GrDino/util/utils.py
GrDino/util/visualizer.py
GrDino/util/vl_utils.py