Metadata-Version: 2.1
Name: GrDino
Version: 0.2.4
Summary: open-set object detector
Home-page: https://github.com/cveatt/GroundingDinoCommit
Author: cveatt
License:                                  Apache License
Platform: UNKNOWN
License-File: LICENSE
